botbuilder/community/dialogs/prompts/__init__.py
botbuilder/community/dialogs/prompts/about.py
botbuilder/community/dialogs/prompts/email_prompt.py
botbuilder/community/dialogs/prompts/guid_prompt.py
botbuilder/community/dialogs/prompts/internet_protocol_prompt.py
botbuilder/community/dialogs/prompts/number_with_type_prompt.py
botbuilder/community/dialogs/prompts/number_with_unit_prompt.py
botbuilder/community/dialogs/prompts/phone_prompt.py
botbuilder_community_dialogs_prompts-0.1.3.dist-info/METADATA
botbuilder_community_dialogs_prompts-0.1.3.dist-info/WHEEL
botbuilder_community_dialogs_prompts-0.1.3.dist-info/top_level.txt
botbuilder_community_dialogs_prompts-0.1.3.dist-info/RECORD
