Metadata-Version: 2.1
Name: botbuilder-community-dialogs-prompts
Version: 0.1.3
Summary: Microsoft Bot Builder Community Dialogs Prompts
Home-page: https://github.com/BotBuilderCommunity/botbuilder-community-python
Author: Bot Builder Community
License: MIT
Keywords: botbuilder bots ai botframework dialogs prompts
Platform: UNKNOWN
Classifier: Programming Language :: Python :: 3.7
Classifier: Intended Audience :: Developers
Classifier: License :: OSI Approved :: MIT License
Classifier: Operating System :: OS Independent
Classifier: Development Status :: 3 - Alpha
Classifier: Topic :: Scientific/Engineering :: Artificial Intelligence
Requires-Dist: botbuilder-core (>=4.5.0b5)
Requires-Dist: botbuilder-schema (>=4.5.0b5)
Requires-Dist: botbuilder-dialogs (>=4.5.0b5)
Requires-Dist: recognizers-text-suite (>=1.0.2a2)
Requires-Dist: aiounittest (>=1.3.0)
